translateAPI/__init__.py
translateAPI/translateAPI.py
translation_api_python_client-1.0.0.dist-info/LICENSE
translation_api_python_client-1.0.0.dist-info/METADATA
translation_api_python_client-1.0.0.dist-info/WHEEL
translation_api_python_client-1.0.0.dist-info/top_level.txt
translation_api_python_client-1.0.0.dist-info/RECORD
